LICENSE
MANIFEST.in
README.md
setup.cfg
setup.py
tap_emarsys/__init__.py
tap_emarsys/context.py
tap_emarsys/http.py
tap_emarsys/schemas.py
tap_emarsys/streams.py
tap_emarsys.egg-info/PKG-INFO
tap_emarsys.egg-info/SOURCES.txt
tap_emarsys.egg-info/dependency_links.txt
tap_emarsys.egg-info/entry_points.txt
tap_emarsys.egg-info/requires.txt
tap_emarsys.egg-info/top_level.txt
tap_emarsys/schemas/campaigns.json
tap_emarsys/schemas/contact_list_memberships.json
tap_emarsys/schemas/contact_lists.json
tap_emarsys/schemas/metrics.json