Metadata-Version: 1.1
Name: tap-emarsys
Version: 0.4.0
Summary: Singer.io tap for extracting data from the Emarsys API
Home-page: http://singer.io
Author: Stitch
Author-email: UNKNOWN
License: UNKNOWN
Platform: UNKNOWN
Classifier: Programming Language :: Python :: 3 :: Only
